pride_flags/__init__.py
pride_flags/entry.py
pride_flags/flags.py
cli_pride_flags_python-1.2.0.dist-info/LICENSE
cli_pride_flags_python-1.2.0.dist-info/METADATA
cli_pride_flags_python-1.2.0.dist-info/WHEEL
cli_pride_flags_python-1.2.0.dist-info/entry_points.txt
cli_pride_flags_python-1.2.0.dist-info/top_level.txt
cli_pride_flags_python-1.2.0.dist-info/RECORD
