Metadata-Version: 2.1
Name: cli-pride-flags-python
Version: 1.2.0
Summary: Generate Pride flags in your terminal with python!
Author: ItzSulfur
Project-URL: Homepage, https://github.com/ItzSulfur/cli-pride-flags-python
License-File: LICENSE
Requires-Dist: colored
